stravainteractweblib/__init__.py
stravainteractweblib/interactwebclient.py
stravainteractweblib-0.0.5.dist-info/LICENSE
stravainteractweblib-0.0.5.dist-info/METADATA
stravainteractweblib-0.0.5.dist-info/WHEEL
stravainteractweblib-0.0.5.dist-info/top_level.txt
stravainteractweblib-0.0.5.dist-info/RECORD
