Metadata-Version: 2.1
Name: stravainteractweblib
Version: 0.0.5
Summary: Extends the Strava v3 API using web scraping and web browser interactions
Home-page: https://github.com/ConstantinB9/stravainteractweblib
License: MPLv2
Classifier: Intended Audience :: Developers
Classifier: Topic :: Software Development :: Libraries :: Python Modules
Classifier: Programming Language :: Python :: 3
Classifier: Programming Language :: Python :: 3.4
Classifier: Programming Language :: Python :: 3.5
Classifier: Programming Language :: Python :: 3.6
Classifier: Programming Language :: Python :: 3.7
Classifier: Programming Language :: Python :: 3.8
Classifier: Programming Language :: Python :: 3.9
Classifier: Programming Language :: Python :: 3.10
Classifier: Operating System :: OS Independent
Classifier: License :: OSI Approved :: Mozilla Public License 2.0 (MPL 2.0)
Requires-Python: >=3.4.0
License-File: LICENSE
Requires-Dist: stravaweblib (>=0.0.6)
Requires-Dist: mechanize (>=0.4.8)
